pgcronner-0.1.14.dist-info/METADATA
pgcronner-0.1.14.dist-info/WHEEL
pgcronner-0.1.14.dist-info/license_files/LICENSE
pgcronner/__init__.py
pgcronner/__init__.pyi
pgcronner/py.typed
pgcronner/pgcronner.cpython-311-x86_64-linux-gnu.so
pgcronner-0.1.14.dist-info/RECORD
