Metadata-Version: 2.1
Name: pgcronner
Version: 0.1.14
Classifier: Programming Language :: Rust
Classifier: Programming Language :: Python :: Implementation :: CPython
Classifier: Programming Language :: Python :: Implementation :: PyPy
License-File: LICENSE
Summary: Fast pgcron manager written in Rust
Author-email: Abel Hristodor <habelor@gmail.com>
Requires-Python: >=3.8
Project-URL: Homepage, https://github.com/AbelHristodor/pgcronner
